CHANGELOG
LICENSE
MANIFEST.in
README.rst
distribute_setup.py
setup.py
docs/Makefile
docs/api.rst
docs/benchmark_dict.py
docs/benchmark_trie.py
docs/conf.py
docs/guide.rst
docs/index.rst
docs/issues.rst
docs/overview.rst
docs/_build/doctrees/api.doctree
docs/_build/doctrees/environment.pickle
docs/_build/doctrees/guide.doctree
docs/_build/doctrees/index.doctree
docs/_build/doctrees/issues.doctree
docs/_build/doctrees/overview.doctree
docs/_build/html/.buildinfo
docs/_build/html/api.html
docs/_build/html/genindex.html
docs/_build/html/guide.html
docs/_build/html/index.html
docs/_build/html/issues.html
docs/_build/html/objects.inv
docs/_build/html/overview.html
docs/_build/html/search.html
docs/_build/html/searchindex.js
docs/_build/html/_modules/index.html
docs/_build/html/_modules/prefixtree.html
docs/_build/html/_sources/api.txt
docs/_build/html/_sources/guide.txt
docs/_build/html/_sources/index.txt
docs/_build/html/_sources/issues.txt
docs/_build/html/_sources/overview.txt
docs/_build/html/_static/agogo.css
docs/_build/html/_static/ajax-loader.gif
docs/_build/html/_static/basic.css
docs/_build/html/_static/bgfooter.png
docs/_build/html/_static/bgtop.png
docs/_build/html/_static/comment-bright.png
docs/_build/html/_static/comment-close.png
docs/_build/html/_static/comment.png
docs/_build/html/_static/doctools.js
docs/_build/html/_static/down-pressed.png
docs/_build/html/_static/down.png
docs/_build/html/_static/file.png
docs/_build/html/_static/jquery.js
docs/_build/html/_static/minus.png
docs/_build/html/_static/plus.png
docs/_build/html/_static/pygments.css
docs/_build/html/_static/searchtools.js
docs/_build/html/_static/underscore.js
docs/_build/html/_static/up-pressed.png
docs/_build/html/_static/up.png
docs/_build/html/_static/websupport.js
docs/_templates/page.html
prefixtree/__init__.py
prefixtree/collections.py
prefixtree/trie.py
prefixtree/version.py
prefixtree.egg-info/PKG-INFO
prefixtree.egg-info/SOURCES.txt
prefixtree.egg-info/dependency_links.txt
prefixtree.egg-info/not-zip-safe
prefixtree.egg-info/top_level.txt
tests/__init__.py
tests/test_prefixdict.py
tests/test_prefixset.py
tests/test_prefixtree.py
